README.rst
setup.py
jpake/__init__.py
jpake/exceptions.py
jpake/parameters.py
jpake/values.py
jpake.egg-info/PKG-INFO
jpake.egg-info/SOURCES.txt
jpake.egg-info/dependency_links.txt
jpake.egg-info/top_level.txt
jpake/tests/__init__.py