Metadata-Version: 1.1
Name: jpake
Version: 0.6.0
Summary: Implementation of the J-PAKE password authenticated key agreement algorithm
Home-page: github.com/bwhmather/python-jpake
Author: Ben Mather
Author-email: bwhmather@bwhmather.com
License: BSD
Platform: UNKNOWN
Classifier: Development Status :: 4 - Beta
Classifier: Intended Audience :: Developers
Classifier: License :: OSI Approved :: BSD License
Classifier: Operating System :: OS Independent
Classifier: Programming Language :: Python :: 3
Classifier: Topic :: Software Development :: Libraries :: Python Modules
